pyarrow_message-0.1.5.dist-info/METADATA
pyarrow_message-0.1.5.dist-info/WHEEL
pyarrow_message-0.1.5.dist-info/licenses/LICENSE
pyarrow_message/__init__.py
pyarrow_message/__init__.pyi
pyarrow_message/pyarrow_message.pypy39-pp73-arm-linux-gnu.so
pyarrow_message-0.1.5.dist-info/RECORD
