Metadata-Version: 2.4
Name: pyarrow_message
Version: 0.1.5
Classifier: Programming Language :: Rust
Classifier: Programming Language :: Python :: Implementation :: CPython
Classifier: Programming Language :: Python :: Implementation :: PyPy
Requires-Dist: numpy>=1.24.4
Requires-Dist: pyarrow>=17.0.0
Requires-Dist: pytest ; extra == 'tests'
Requires-Dist: ruff>=0.11.1 ; extra == 'tests'
Provides-Extra: tests
License-File: LICENSE
Summary: arrow-message implements a way to define messages according to the Arrow format in both Rust and Python
License: Apache-2.0
Requires-Python: >=3.8
Project-URL: Source Code, https://github.com/Hennzau/arrow-message
